c5pkg/__init__.py
c5pkg/add.py
c5pkg/subtract.py
c5pkg/extras/__init__.py
c5pkg/extras/divide.py
c5pkg/extras/multiply.py
c5pkg-0.0.3.dist-info/METADATA
c5pkg-0.0.3.dist-info/WHEEL
c5pkg-0.0.3.dist-info/top_level.txt
c5pkg-0.0.3.dist-info/RECORD
