Metadata-Version: 2.4
Name: c5pkg
Version: 0.0.3
Summary: simple package for ai
Author: C5m7b4
Author-email: c5m7b4@gmail.com
Keywords: python,first package
Dynamic: author
Dynamic: author-email
Dynamic: description
Dynamic: keywords
Dynamic: summary
